mlforget/__init__.py
mlforget/data_utils.py
mlforget/evaluation.py
mlforget/model_utils.py
mlforget/training.py
mlforget/unlearning.py
mlforget/workflow.py
mlforget-0.1.0.dist-info/LICENSE
mlforget-0.1.0.dist-info/METADATA
mlforget-0.1.0.dist-info/WHEEL
mlforget-0.1.0.dist-info/top_level.txt
mlforget-0.1.0.dist-info/RECORD
