Metadata-Version: 2.1
Name: mlforget
Version: 0.1.0
Summary: Machine unlearning methods for energy consumption prediction
Home-page: https://github.com/Kaiboy55/MLForget
Author: Kai Pinas
Author-email: kai.pinas@student.uva.nl
License: MIT
Classifier: Programming Language :: Python :: 3
Classifier: License :: OSI Approved :: MIT License
Classifier: Operating System :: OS Independent
Requires-Python: >=3.7
License-File: LICENSE
Requires-Dist: torch
Requires-Dist: numpy
Requires-Dist: pandas
Requires-Dist: scikit-learn
